nephased/__init__.py
nephased/model.py
nephased-0.0.34.dist-info/licenses/LICENSE
nephased-0.0.34.dist-info/METADATA
nephased-0.0.34.dist-info/WHEEL
nephased-0.0.34.dist-info/top_level.txt
nephased-0.0.34.dist-info/RECORD
