Metadata-Version: 2.4
Name: nephased
Version: 0.0.34
Summary: A BERT-based text sentiment classification pipeline for Nepali Language
Author-email: Angel Tamang <tamangangel2057@gmail.com>, Aadarsha Regmi <aadarsha.regmi11@gmail.com>, Gaurav Maharjan <gauravmaharjan1@gmail.com>, Anil Bhatta <bhattaanil1234@gmail.com>
License: MIT
Project-URL: Homepage, https://github.com/angeltamang123/nephased
Project-URL: Source, https://github.com/angeltamang123/nephased
Keywords: nlp,transformers,bert,nepali,nephased,sentiment
Classifier: Programming Language :: Python :: 3
Classifier: License :: OSI Approved :: MIT License
Classifier: Operating System :: OS Independent
Requires-Python: >=3.10
License-File: LICENSE
Requires-Dist: nepali-stemmer>=0.0.2
Requires-Dist: nltk>=3.9.1
Requires-Dist: safetensors>=0.5.0
Requires-Dist: importlib_resources==6.5.2
Provides-Extra: ml
Requires-Dist: torch>=2.0.0; extra == "ml"
Requires-Dist: transformers[sentencepiece]>=4.20.0; extra == "ml"
Provides-Extra: optimum
Requires-Dist: optimum>=1.16.0; extra == "optimum"
Provides-Extra: dev
Requires-Dist: nephased[ml,optimum]; extra == "dev"
Dynamic: license-file
